peewee_ext/__init__.py
peewee_ext/database.py
peewee_ext/decorator.py
peewee_ext/logger.py
peewee_ext/model.py
peewee_ext/version.py
peewee_ext-0.0.2.dist-info/METADATA
peewee_ext-0.0.2.dist-info/WHEEL
peewee_ext-0.0.2.dist-info/top_level.txt
peewee_ext-0.0.2.dist-info/zip-safe
peewee_ext-0.0.2.dist-info/RECORD
