Metadata-Version: 2.1
Name: peewee-ext
Version: 0.0.2
Summary: peewee-ext is a peewee extension
Home-page: https://github.com/mouday/peewee-ext
Author: Peng Shiyu
Author-email: pengshiyuyx@gmail.com
License: MIT
Keywords: peewee,mysql,pymysql,sqlite,dict
Platform: UNKNOWN
Classifier: Programming Language :: Python :: 3
Classifier: Programming Language :: Python :: 3.7
Requires-Dist: peewee
